boolsi/__init__.py
boolsi/attract.py
boolsi/attractor_analysis.py
boolsi/batching.py
boolsi/cli.py
boolsi/constants.py
boolsi/db.py
boolsi/input.py
boolsi/log.py
boolsi/model.py
boolsi/mpi.py
boolsi/output.py
boolsi/simulate.py
boolsi/target.py
boolsi/testing_tools.py
boolsi/utils.py
boolsi-1.0.5.dist-info/licenses/LICENSE.txt
boolsi-1.0.5.dist-info/METADATA
boolsi-1.0.5.dist-info/WHEEL
boolsi-1.0.5.dist-info/entry_points.txt
boolsi-1.0.5.dist-info/top_level.txt
boolsi-1.0.5.dist-info/RECORD
